{"is_source_file": false, "format": "", "description": "", "external_files": [], "external_methods": [], "published": [], "classes": [], "methods": [], "calls": [], "search-terms": ["note-organizer", "README.md", "393-403"], "state": 2, "file_id": 5, "knowledge_revision": 7, "git_revision": "3775d5ce9b7cd734ec99f1cc4a36408122c83905", "hash": "06b742b681f3f860ef763f791e816666", "format-version": 4, "code-base-name": "notes_database", "filename": "README.md", "revision_history": [{"7": "3775d5ce9b7cd734ec99f1cc4a36408122c83905"}]}